LICENSE.txt
README.md
setup.cfg
setup.py
motif_learn.egg-info/PKG-INFO
motif_learn.egg-info/SOURCES.txt
motif_learn.egg-info/dependency_links.txt
motif_learn.egg-info/requires.txt
motif_learn.egg-info/top_level.txt
mtflearn/__init__.py